fast.py
setup.py
fast.com.egg-info/PKG-INFO
fast.com.egg-info/SOURCES.txt
fast.com.egg-info/dependency_links.txt
fast.com.egg-info/entry_points.txt
fast.com.egg-info/requires.txt
fast.com.egg-info/top_level.txt