Metadata-Version: 1.0
Name: fast.com
Version: 1.0.2
Summary: fast.com speedtest cli
Home-page: https://github.com/banteg/fast
Author: banteg
Author-email: UNKNOWN
License: MIT
Platform: UNKNOWN
